fatush/__init__.py
fatush/search_engine.py
fatush/search_word.py
fatush/utils/__init__.py
fatush/utils/config.py
fatush/utils/engine.py
fatush/utils/script.py
fatush-0.1.0.dist-info/METADATA
fatush-0.1.0.dist-info/WHEEL
fatush-0.1.0.dist-info/entry_points.txt
fatush-0.1.0.dist-info/RECORD
