Metadata-Version: 2.1
Name: fatush
Version: 0.1.0
Summary: Simple utility tools for translating fastapi documentation
License: MIT
Author: Alper Balbay
Author-email: itsc0508@gmail.com
Requires-Python: >=3.11,<4.0
Classifier: License :: OSI Approved :: MIT License
Classifier: Programming Language :: Python :: 3
Classifier: Programming Language :: Python :: 3.11
Requires-Dist: beautifulsoup4 (>=4.12.3,<5.0.0)
Requires-Dist: faiss-cpu (>=1.7.4,<2.0.0)
Requires-Dist: fastapi[all] (>=0.109.1,<0.110.0)
Requires-Dist: huggingface (>=0.0.1,<0.0.2)
Requires-Dist: langchain (>=0.1.5,<0.2.0)
Requires-Dist: markdown (>=3.5.2,<4.0.0)
Requires-Dist: rich (>=13.7.0,<14.0.0)
Requires-Dist: sentence-transformers (>=2.3.1,<3.0.0)
Requires-Dist: typer (>=0.9.0,<0.10.0)
